matrixmethod/__init__.py
matrixmethod/example_usage.ipynb
matrixmethod/mm_numba.py
matrixmethod/mm_pure_python.py
matrixmethod/mm_pure_python_p_pol.py
matrixmethod/xrr_interactive.py
matrixmethod-0.1.3.dist-info/METADATA
matrixmethod-0.1.3.dist-info/WHEEL
matrixmethod-0.1.3.dist-info/RECORD
