Metadata-Version: 2.4
Name: matrixmethod
Version: 0.1.3
Summary: Calculating Refelctivity
Author: Mika Pflueger
Author-email: Kas Andrle <kandrle@lbl.gov>
Requires-Python: >=3.12
Requires-Dist: numba>=0.62.0
Requires-Dist: numpy>=1.0.0
